Workbook

Sheet Comparativa
A1: Remuneración LBD - Acuerdo Original (05/07/2024) | E1: Remuneración LBD - TS Firmado (09/02/2026) | H1: Remuneración LBD - Borrador TS v15 (RIO / Altern / Berkes)
B2: MODELO ORIGINAL | C2: MODELO REAL 2026 | F2: USD | L2: OPCIÓN A: PB + Revenue share Altern | M2: OPCIÓN B: PB + Opción Piso 4
A4: BASE | E4: BASE | H4: BASE
A5: Valor llave (a la fin) | B5: 1000000 | C5: 1000000 | E5: Llave a la firma del acuerdo definitivo | F5: 1000000 | H5: Valor llave (al inicio) | L5: 1100000 | M5: =L5
A6: Ganancia Proyecto 10% | B6: =B11*$B$46 | C6: =C11*$B$46 | E6: Llave en 18 cuotas mensuales (durante obra) | F6: 1100000 | H6: Valor llave a fin (95% avance, +6% nom.) | L6: 377000 | M6: =L6
A7: Honorarios desarrollo 50% | B7: 550000 | C7: 612500 | E7: Coronamiento (cochera/box/depósito con uso exclusivo) | F7: s/valorizar
A9: Total | B9: =SUM(B5:B8) | C9: =SUM(C5:C8) | E9: Total | F9: =SUM(F5:F8) | H9: Total | L9: =SUM(L5:L8) | M9: =SUM(M5:M8)
A11: Ganancia TOF | B11: 10592596 | C11: 7592596 | H11: ADICIONALES | I11: un | J11: Valor | K11: Compra
H12: PB RIO (50%) | I12: 700 | J12: 2500 | K12: 1800 | L12: =I12*(J12-K12)*$B$47 | M12: =I12*(J12-K12)*$B$47
H13: Pisos Altern (50%) - revenue share | I13: 1200 | J13: 3900 | K13: 3500 | L13: =I13*(J13-K13)*$B$47 | M13: 0
H14: o opción N4
H15: Nivel 4 TOF | I15: 540 | J15: 4250 | K15: 2970 | L15: 0 | M15: =I15*(J15-K15)*$B$48
H16: Total adicionales | L16: =L12+L13+L15 | M16: =M12+M13+M15
A18: Contingencia LBD | E18: Contingencia LBD | H18: Contingencia
A19: GO FM (4%) | C19: 174800
A20: Pisos Maneiro | C20: 400000 | E20: Pisos Maneiro (lit. D, a confirmar) | F20: 400000 | H20: Pisos Maneiro | L20: 400000 | M20: =L20
A21: Multa Maneiro | B21: 600000 | E21: Multa Maneiro (renunciada, cond. 2.B) | F21: 0
A22: Ganancias - Contingencias | B22: =B9-B19-B20-B21 | C22: =C9-C19-C20-C21 | E22: Ganancias - Contingencias | F22: =F9-F20-F21 | H22: Ganancias - Contingencias | L22: =L9+L16-L20 | M22: =M9+M16-M20
H23: Ref. tabla 22/07 (Piso 4 sin PB) | L23: =L9+M15-L20
A25: Cesiones | E25: Cesiones | H25: Cesiones
H26: GO FM (4%) - informativo, no suma | L26: 174800
A28: Otros | E28: Otros | H28: Otros | I28: un | J28: Valor | K28: Compra
A29: Nivel 4 CCCOM | B29: 1305000 | C29: 0 | H29: Nivel 4 CCCOM | I29: 900 | J29: 3800 | K29: 900 | L29: =I29*(J29-K29)*$B$49 | M29: =L29
A30: Total | B30: =SUM(B29) | C30: =SUM(C29) | H30: Total | L30: =SUM(L29) | M30: =SUM(M29)
A32: Otros: | E32: Otros: | H32: Otros:
A33: En caso que se ejecute la multa de 600 mil USD es a cargo de LBD y gastos de ocupación son ingreso del proyecto. | E33: Multa Maneiro renunciada (cond. 2.B). Gastos de ocupación: Maneiro exonerado en sus unidades (cond. 2.C). | H33: LBD propone descontar Multa de los GO de Maneiro.
A45: SUPUESTOS (celdas azules = inputs)
A46: % LBD en utilidad de CC SRL (cl. 3.3 acuerdo original) | B46: 0.1
A47: % LBD en utilidad PB y revenue share Altern (v15) | B47: 0.5
A48: % LBD en utilidad Piso 4 TOF (v15, aporta 100% del costo) | B48: 1
A49: % LBD en Nivel 4 CCCOM (según tabla 22/07) | B49: 0.5

Sheet Resumen
A1: Resumen comparativo - Remuneración LBD (USD)
A3: Concepto | B3: Original real 2026 | C3: TS firmado 09/02/26 | D3: v15 Opción A (PB + rev. share Altern) | E3: v15 Opción B (PB + Piso 4) | F3: v15 s/ tabla 22/07 (Piso 4 sin PB)
A4: Base (llave + utilidad 10% + honorarios) | B4: =Comparativa!C9 | C4: =Comparativa!F9 | D4: =Comparativa!L9 | E4: =Comparativa!M9 | F4: =Comparativa!L9
A5: Adicionales (PB / revenue share / Piso 4) | B5: 0 | C5: 0 | D5: =Comparativa!L16 | E5: =Comparativa!M16 | F5: =Comparativa!M15
A6: Contingencias (GO FM, Pisos Maneiro, multa) | B6: =-(Comparativa!C19+Comparativa!C20+Comparativa!C21) | C6: =-(Comparativa!F20+Comparativa!F21) | D6: =-Comparativa!L20 | E6: =-Comparativa!M20 | F6: =-Comparativa!L20
A7: Neto Ganancias - Contingencias | B7: =SUM(B4:B6) | C7: =SUM(C4:C6) | D7: =SUM(D4:D6) | E7: =SUM(E4:E6) | F7: =SUM(F4:F6)
A8: Otros: Nivel 4 CCCOM (activo propio de LBD) | B8: =Comparativa!C30 | C8: 0 | D8: =Comparativa!L30 | E8: =Comparativa!M30 | F8: =Comparativa!L30
A9: Neto + Otros | B9: =B7+B8 | C9: =C7+C8 | D9: =D7+D8 | E9: =E7+E8 | F9: =F7+F8
A11: Δ Neto vs Original real 2026 (USD) | B11: =B7-$B$7 | C11: =C7-$B$7 | D11: =D7-$B$7 | E11: =E7-$B$7 | F11: =F7-$B$7
A12: Δ Neto vs Original real 2026 (%) | B12: =IF($B$7=0,0,B11/$B$7) | C12: =IF($B$7=0,0,C11/$B$7) | D12: =IF($B$7=0,0,D11/$B$7) | E12: =IF($B$7=0,0,E11/$B$7) | F12: =IF($B$7=0,0,F11/$B$7)
A13: Δ Base vs Original real 2026 (USD) | B13: =B4-$B$4 | C13: =C4-$B$4 | D13: =D4-$B$4 | E13: =E4-$B$4 | F13: =F4-$B$4
A14: Δ Base vs Original real 2026 (%) | B14: =IF($B$4=0,0,B13/$B$4) | C14: =IF($B$4=0,0,C13/$B$4) | D14: =IF($B$4=0,0,D13/$B$4) | E14: =IF($B$4=0,0,E13/$B$4) | F14: =IF($B$4=0,0,F13/$B$4)
A16: Notas
A17: * TS firmado: no incluye el valor del coronamiento (sin valorizar). La contingencia de 400k (Pisos Maneiro) es un supuesto a confirmar.
A18: Opción A y B son excluyentes entre sí (el revenue share de Altern no aplica si LBD ejerce la opción Piso 4). PB RIO aplica en ambas.
A19: Adicionales del v15 sin descontar: interés 6% nominal sobre aportes (PB y Piso 4), financiamiento del costo del Piso 4 (~USD 1,6 M), IVA y tributos a cargo de LBD.
A20: Sin cuantificar en el v15: opción de cocheras (USD 25.000 c/u), ahorro eventual por tipo de cambio en contrato de obra, reintegro de USD 750.000 de Parque Roosevelt (pass-through) e interés 6% sobre los 377.000.
A21: Sin cuantificar en el acuerdo original: comisión 2% + IVA por ventas impulsadas por LBD (cl. 8).
A22: Nivel 4 CCCOM: figura en el modelo original en 1.305.000 y en 0 en el 'modelo real 2026'; es un activo propio de LBD, no remuneración de Berkes. Se muestra aparte para no inflar la comparación.
A23: Valores nominales, sin descontar. El original paga al final de obra; el v15 paga 1,1 M a la firma y 377k al 95% de avance.
A24: Fuentes: Acuerdo Berkes-LBD 05/07/2024 (cl. 3.3, 4.1, 6, 8); TS firmado 09/02/2026; borrador TS v15 (08/07/2026); COMPARATIVA ACUERDO BERKES - LBD RIO 22/07 (inputs azules).
